momentum/__init__.py
momentum/__main__.py
momentum/cli.py
momentum/display.py
momentum/timer.py
momentum_task-0.1.0.dist-info/METADATA
momentum_task-0.1.0.dist-info/WHEEL
momentum_task-0.1.0.dist-info/entry_points.txt
momentum_task-0.1.0.dist-info/licenses/LICENSE
momentum_task-0.1.0.dist-info/RECORD
