Metadata-Version: 2.4
Name: momentum-task
Version: 0.1.0
Summary: A minimal, one-task-at-a-time CLI tracker with built-in Pomodoro timer
Project-URL: Homepage, https://github.com/DanielWJudge/Momentum
Project-URL: Bug Reports, https://github.com/DanielWJudge/Momentum/issues
Project-URL: Source, https://github.com/DanielWJudge/Momentum
Project-URL: Documentation, https://github.com/DanielWJudge/Momentum#readme
Author-email: Daniel Judge <dwjref+momentum@gmail.com>
License: MIT License
License-File: LICENSE
Keywords: cli,gtd,pomodoro,productivity,task-management,todo
Classifier: Development Status :: 4 - Beta
Classifier: Environment :: Console
Classifier: Intended Audience :: Developers
Classifier: Intended Audience :: End Users/Desktop
Classifier: License :: OSI Approved :: MIT License
Classifier: Operating System :: OS Independent
Classifier: Programming Language :: Python :: 3
Classifier: Programming Language :: Python :: 3.8
Classifier: Programming Language :: Python :: 3.9
Classifier: Programming Language :: Python :: 3.10
Classifier: Programming Language :: Python :: 3.11
Classifier: Programming Language :: Python :: 3.12
Classifier: Topic :: Office/Business :: Scheduling
Classifier: Topic :: Utilities
Requires-Python: >=3.8
